{"cameraMode":{"drawMode":0,"name":"Shaded","section":"Shading Mode"},"sceneLighting":true,"audioPlay":false,"sceneViewState":{"showFog":true,"showMaterialUpdate":false,"showSkybox":true,"showFlares":true,"showImageEffects":true,"showParticleSystems":true},"in2DMode":false,"pivot":{"x":-94.84798431396485,"y":-160.6413116455078,"z":79.62026977539063},"rotation":{"x":-0.3940410315990448,"y":0.40361976623535159,"z":-0.19842484593391419,"w":-0.8015300631523132},"size":215.09510803222657,"orthographic":false}